lightchat/__init__.py
lightchat/__version__.py
lightchat/constants.py
lightchat/exceptions.py
lightchat/api/__init__.py
lightchat/api/process.py
lightchat/api/runtime.py
lightchat/config/__init__.py
lightchat/config/core.py
lightchat/config/defaults.py
lightchat/config/loader.py
lightchat/config/schema.py
lightchat/ipc/__init__.py
lightchat/ipc/channel.py
lightchat/ipc/core.py
lightchat/ipc/protocol.py
lightchat/ipc/queue.py
lightchat/observability/__init__.py
lightchat/observability/core.py
lightchat/observability/logging.py
lightchat/observability/metrics.py
lightchat/resources/__init__.py
lightchat/resources/core.py
lightchat/resources/limits.py
lightchat/resources/monitor.py
lightchat/resources/quotas.py
lightchat/runtime/__init__.py
lightchat/runtime/process.py
lightchat/runtime/runtime_core.py
lightchat/runtime/signals.py
lightchat/runtime/state.py
lightchat/runtime/supervisor.py
lightchat/security/__init__.py
lightchat/security/core.py
lightchat/security/permissions.py
lightchat/security/policy.py
lightchat/security/sandbox.py
lightchat-1.0.0.dist-info/licenses/LICENSE
lightchat-1.0.0.dist-info/METADATA
lightchat-1.0.0.dist-info/WHEEL
lightchat-1.0.0.dist-info/top_level.txt
lightchat-1.0.0.dist-info/RECORD
