Metadata-Version: 2.4
Name: lightchat
Version: 1.0.0
Summary: LightChat is a deterministic, secure, and production-grade runtime for controlled conversational processes.
Author: Ganesh Nalawade
Maintainer: repromptsquest
License: 
Project-URL: Homepage, https://github.com/your-username/lightchat
Project-URL: Documentation, https://github.com/your-username/lightchat#readme
Project-URL: Source, https://github.com/your-username/lightchat
Project-URL: Issues, https://github.com/your-username/lightchat/issues
Keywords: chat,runtime,process-management,sandbox,deterministic,observability,ipc,security
Classifier: Development Status :: 5 - Production/Stable
Classifier: Intended Audience :: Developers
Classifier: Intended Audience :: Information Technology
Classifier: License :: OSI Approved :: MIT License
Classifier: Programming Language :: Python :: 3
Classifier: Programming Language :: Python :: 3.9
Classifier: Programming Language :: Python :: 3.10
Classifier: Programming Language :: Python :: 3.11
Classifier: Programming Language :: Python :: 3.12
Classifier: Operating System :: OS Independent
Classifier: Topic :: Software Development :: Libraries
Classifier: Topic :: Software Development :: Libraries :: Application Frameworks
Classifier: Topic :: System :: Monitoring
Classifier: Topic :: Security
Requires-Python: >=3.9
License-File: LICENSE
Requires-Dist: psutil>=5.9.0
Provides-Extra: dev
Requires-Dist: black>=23.0; extra == "dev"
Requires-Dist: ruff>=0.0.280; extra == "dev"
Requires-Dist: mypy>=1.5; extra == "dev"
Requires-Dist: build>=1.0; extra == "dev"
Requires-Dist: twine>=4.0; extra == "dev"
Provides-Extra: docs
Requires-Dist: mkdocs>=1.5; extra == "docs"
Requires-Dist: mkdocs-material>=9.0; extra == "docs"
Dynamic: license-file
